[
    {
        "ID": "01",
        "Name": "Android"
    },
    {
        "ID": "02",
        "Name": "API"
    },
    {
        "ID": "03",
        "Name": "cloud"
    },
    {
        "ID": "04",
        "Name": "web"
    },
    {
        "ID": "05",
        "Name": "mobile"
    },
    {
        "ID": "06",
        "Name": "SAP"
    },
    {
        "ID": "07",
        "Name": "HUB"
    },
    {
        "ID": "08",
        "Name": "Agile"
    },
    {
        "ID": "09",
        "Name": "Angular"
    },
    {
        "ID": "10",
        "Name": "React"
    },
    {
        "ID": "11",
        "Name": "iOS"
    }
]